<?xml version="1.0" encoding="UTF-8" ?>
<!--
 *  Copyright (c) 2001-2005 The Open For Business Project - www.ofbiz.org
 *
 *  Permission is hereby granted, free of charge, to any person obtaining a
 *  copy of this software and associated documentation files (the "Software"),
 *  to deal in the Software without restriction, including without limitation
 *  the rights to use, copy, modify, merge, publish, distribute, sublicense,
 *  and/or sell copies of the Software, and to permit persons to whom the
 *  Software is furnished to do so, subject to the following conditions:
 *
 *  The above copyright notice and this permission notice shall be included
 *  in all copies or substantial portions of the Software.
 *
 *  THE SOFTWARE IS PROVIDED "AS IS", WITHOUT WARRANTY OF ANY KIND, EXPRESS
 *  OR IMPLIED, INCLUDING BUT NOT LIMITED TO THE WARRANTIES OF
 *  MERCHANTABILITY, FITNESS FOR A PARTICULAR PURPOSE AND NONINFRINGEMENT.
 *  IN NO EVENT SHALL THE AUTHORS OR COPYRIGHT HOLDERS BE LIABLE FOR ANY
 *  CLAIM, DAMAGES OR OTHER LIABILITY, WHETHER IN AN ACTION OF CONTRACT, TORT
 *  OR OTHERWISE, ARISING FROM, OUT OF OR IN CONNECTION WITH THE SOFTWARE OR
 *  THE USE OR OTHER DEALINGS IN THE SOFTWARE.
 
 * OpenTravelSystem additional services on top of the OFBiz services. 
-->

<!--  =============== Open Travel System additional services ===================== -->
<services xmlns:xsi="http://www.w3.org/2001/XMLSchema-instance"
    xsi:noNamespaceSchemaLocation="http://www.ofbiz.org/dtds/services.xsd">
    <description>OpenTravelSystemServices</description>
    <vendor>OFBiz</vendor>
    <version>1.0</version>
    
    <!-- party services to add, update and logically delete. -->
    <service name="otsAddParty" engine="simple" location="org/ofbiz/opentravelsystem/PartyServices.xml"
        invoke="addParty" auth="true">
        <description>Add a new party to the system and the relationship to the logonnPartyId</description>
        <attribute name="partyId" type="String" mode="OUT" optional="true"/>
        <attribute name="partyRelationshipTypeId" type="String" mode="IN" optional="false"/>
        <attribute name="groupName" type="String" mode="IN" optional="false"/>
        <attribute name="address1" type="String" mode="IN" optional="true"/>
        <attribute name="address2" type="String" mode="IN" optional="true"/>
        <attribute name="city" type="String" mode="IN" optional="true"/>
        <attribute name="postalCode" type="String" mode="IN" optional="true"/>
        <attribute name="countryGeoId" type="String" mode="IN" optional="true"/>
        <attribute name="emailAddress" type="String" mode="IN" optional="true"/>
        <attribute name="telephone" type="String" mode="IN" optional="true"/>
        <attribute name="fax" type="String" mode="IN" optional="true"/>
        <attribute name="accountNumber" type="String" mode="IN" optional="true"/>
    </service>

    <service name="otsGetParty" engine="simple" location="org/ofbiz/opentravelsystem/PartyServices.xml"
        invoke="getParty" auth="true">
        <description>Retrieve the party information</description>
        <attribute name="partyId" type="String" mode="INOUT" optional="true"/>
        <attribute name="partyRelationshipTypeId" type="String" mode="OUT" optional="true"/>
        <attribute name="groupName" type="String" mode="OUT" optional="true"/>
        <attribute name="logoImageUrl" type="String" mode="OUT" optional="true"/>
        <attribute name="address1" type="String" mode="OUT" optional="true"/>
        <attribute name="address2" type="String" mode="OUT" optional="true"/>
        <attribute name="city" type="String" mode="OUT" optional="true"/>
        <attribute name="postalCode" type="String" mode="OUT" optional="true"/>
        <attribute name="countryGeoId" type="String" mode="OUT" optional="true"/>
        <attribute name="emailAddress" type="String" mode="OUT" optional="true"/>
        <attribute name="telephone" type="String" mode="OUT" optional="true"/>
        <attribute name="fax" type="String" mode="OUT" optional="true"/>
        <attribute name="accountNumber" type="String" mode="OUT" optional="true"/>
    </service>
    
    <service name="otsGetOrganizationParty" engine="simple" location="org/ofbiz/opentravelsystem/PartyServices.xml"
        invoke="getOrganizationParty" auth="true">
        <description>Retrieve the organization party information (partyId from the loginId)</description>
        <attribute name="groupName" type="String" mode="OUT" optional="true"/>
        <attribute name="logoImageUrl" type="String" mode="OUT" optional="true"/>
        <attribute name="address1" type="String" mode="OUT" optional="true"/>
        <attribute name="address2" type="String" mode="OUT" optional="true"/>
        <attribute name="city" type="String" mode="OUT" optional="true"/>
        <attribute name="postalCode" type="String" mode="OUT" optional="true"/>
        <attribute name="countryGeoId" type="String" mode="OUT" optional="true"/>
        <attribute name="emailAddress" type="String" mode="OUT" optional="true"/>
        <attribute name="telephone" type="String" mode="OUT" optional="true"/>
        <attribute name="fax" type="String" mode="OUT" optional="true"/>
        <attribute name="accountNumber" type="String" mode="OUT" optional="true"/>
        <attribute name="baseCurrencyUomId" type="String" mode="OUT" optional="true"/>
    </service>
    
    <service name="otsUpdateParty" engine="simple"
        location="org/ofbiz/opentravelsystem/PartyServices.xml" invoke="updateParty" auth="true">
        <description>Modify the party information including the relationship to the organizationPartyId</description>
        <attribute name="partyId" type="String" mode="INOUT" optional="true"/>
        <attribute name="groupName" type="String" mode="IN" optional="true"/>
        <attribute name="logoImageUrl" type="String" mode="IN" optional="true"/>
        <attribute name="address1" type="String" mode="IN" optional="true"/>
        <attribute name="address2" type="String" mode="IN" optional="true"/>
        <attribute name="city" type="String" mode="IN" optional="true"/>
        <attribute name="postalCode" type="String" mode="IN" optional="true"/>
        <attribute name="countryGeoId" type="String" mode="IN" optional="true"/>
        <attribute name="emailAddress" type="String" mode="IN" optional="true"/>
        <attribute name="telephone" type="String" mode="IN" optional="true"/>
        <attribute name="fax" type="String" mode="IN" optional="true"/>
        <attribute name="accountNumber" type="String" mode="IN" optional="true"/>
    </service>

    <service name="otsUpdateOrganizationParty" engine="simple"
        location="org/ofbiz/opentravelsystem/PartyServices.xml" invoke="updateOrganizationParty" auth="true">
        <description>Modify the party organization information</description>
        <attribute name="groupName" type="String" mode="IN" optional="true"/>
        <attribute name="logoImageUrl" type="String" mode="IN" optional="true"/>
        <attribute name="address1" type="String" mode="IN" optional="true"/>
        <attribute name="address2" type="String" mode="IN" optional="true"/>
        <attribute name="city" type="String" mode="IN" optional="true"/>
        <attribute name="postalCode" type="String" mode="IN" optional="true"/>
        <attribute name="countryGeoId" type="String" mode="IN" optional="true"/>
        <attribute name="emailAddress" type="String" mode="IN" optional="true"/>
        <attribute name="webSite" type="String" mode="IN" optional="true"/>
        <attribute name="telephone" type="String" mode="IN" optional="true"/>
        <attribute name="fax" type="String" mode="IN" optional="true"/>
        <attribute name="bankName" type="String" mode="IN" optional="true"/>
        <attribute name="routingCode" type="String" mode="IN" optional="true"/>
        <attribute name="accountNumber" type="String" mode="IN" optional="true"/>
        <attribute name="baseCurrencyUomId" type="String" mode="IN" optional="true"/>
    </service>
    
    <service name="otsSetStatusParty" engine="simple"
        location="org/ofbiz/opentravelsystem/PartyServices.xml" invoke="setStatusParty" auth="true">
        <description>set the status of a party in thge relationship table</description>
        <attribute name="partyId" type="String" mode="IN" optional="false"/>
        <attribute name="statusId" type="String" mode="IN" optional="false"/>
    </service>
    
    <service name="otsCreatePartyRelationship" engine="simple"
        location="org/ofbiz/opentravelsystem/PartyServices.xml" invoke="createPartyRelationship" auth="true">
        <description>set the relationship between the party and the organizationParty</description>
        <attribute name="partyId" type="String" mode="IN" optional="false"/>
        <attribute name="partyRelationshipTypeId" type="String" mode="IN" optional="true"/>
    </service>
    
    <service name="otsUpdatePostalAddress" engine="simple"
        location="org/ofbiz/opentravelsystem/PartyServices.xml" invoke="updatePostalAddress" auth="true">
        <description>Add or Update a GeneralLocation postal address</description>
        <attribute name="partyId" type="String" mode="IN" optional="false"/>
        <attribute name="address1" type="String" mode="IN" optional="true"/>
        <attribute name="address2" type="String" mode="IN" optional="true"/>
        <attribute name="city" type="String" mode="IN" optional="true"/>
        <attribute name="postalCode" type="String" mode="IN" optional="true"/>
        <attribute name="countryGeoId" type="String" mode="IN" optional="true"/>
    </service>
    
    <service name="otsGetPostalAddress" engine="simple"
        location="org/ofbiz/opentravelsystem/PartyServices.xml" invoke="getPostalAddress" auth="true">
        <description>Get a GeneralLocation postal address</description>
        <attribute name="partyId" type="String" mode="IN" optional="false"/>
        <attribute name="contactMechId" type="String" mode="OUT" optional="true"/>
        <attribute name="address1" type="String" mode="OUT" optional="true"/>
        <attribute name="address2" type="String" mode="OUT" optional="true"/>
        <attribute name="city" type="String" mode="OUT" optional="true"/>
        <attribute name="postalCode" type="String" mode="OUT" optional="true"/>
        <attribute name="countryGeoId" type="String" mode="OUT" optional="true"/>
    </service>

    <service name="otsVatReport" engine="simple"
        location="org/ofbiz/opentravelsystem/ReportServices.xml" invoke="vatReport" auth="true">
        <description>Report on in/out going VAT for a certain time period</description>
        <attribute name="year" type="String" mode="IN" optional="false"/>
        <attribute name="monthList" type="java.util.List" mode="OUT" optional="true"/>
        <attribute name="partyId" type="String" mode="OUT" optional="true"/>
    </service>
    
    <service name="otsOpenInvoiceReport" engine="simple"
        location="org/ofbiz/opentravelsystem/ReportServices.xml" invoke="openInvoiceReport" auth="true">
        <description>Report not completely applied invoices</description>
        <attribute name="openInvoices" type="java.util.List" mode="OUT" optional="true"></attribute>
        <attribute name="partyId" type="String" mode="OUT" optional="true"/>
    </service>
    
    <service name="otsOpenPaymentReport" engine="simple"
        location="org/ofbiz/opentravelsystem/ReportServices.xml" invoke="openPaymentReport" auth="true">
        <description>Report not completely applied payments</description>
        <attribute name="openPayments" type="java.util.List" mode="OUT" optional="true"></attribute>
        <attribute name="partyId" type="String" mode="OUT" optional="true"/>
    </service>
    
    <!-- catalog/product services -->
    <service name="CreateProductCategoryLinkToProdCatalog" engine="simple"
        location="org/ofbiz/opentravelsystem/CatalogServices.xml"
        invoke="CreateProductCategoryLinkToProdCatalog" auth="true">
        <description>Create a new category and make the link to the Catalog</description>
        <attribute name="prodCatalogId" type="String" mode="IN" optional="false"/>
        <attribute name="productCategoryId" type="String" mode="INOUT" optional="true"/>
        <attribute name="primaryParentCategoryId" type="String" mode="IN"/>
        <attribute name="prodCatalogCategoryTypeId" type="String" mode="IN" optional="false"/>
        <attribute name="fromDate" type="String" mode="IN" optional="true"/>
        <attribute name="description" type="String" mode="IN" optional="true"/>
        <attribute name="prodCatalogCategoryTypeId" type="String" mode="IN" optional="false"/>
    </service>

    <!-- general  services -->
    <service name="otsHelp" engine="simple" 
        location="org/ofbiz/opentravelsystem/GeneralServices.xml"
        invoke="help" auth="false">
        <description>Provide the user with information about a certain part of the system</description>
        <attribute name="app" type="String" mode="IN" optional="true"/>
        <attribute name="function" type="String" mode="IN" optional="true"/>
        <attribute name="tab" type="String" mode="IN" optional="true"/>
        <attribute name="contentId" type="String" mode="OUT" optional="true"/>
        <attribute name="dataResourceId" type="String" mode="OUT" optional="true"/>
    </service>
    
    <service name="otsUpdateHelp" engine="simple"
        location="org/ofbiz/opentravelsystem/GeneralServices.xml"
        invoke="updateHelp" auth="true">
        <description>Update the system help</description>
        <attribute name="app" type="String" mode="IN"/>
        <attribute name="function" type="String" mode="IN"/>
        <attribute name="tab" type="String" mode="IN"/>
        <attribute name="textData" type="String" mode="IN"/>
    </service>
    
    <service name="otsEditCmsPage" engine="simple" 
        location="org/ofbiz/opentravelsystem/GeneralServices.xml"
        invoke="editCmsPage" auth="false">
        <description>Edit a html page from the content management system and if not exist create with default info</description>
        <attribute name="contentId" type="String" mode="OUT" optional="true"/>
        <attribute name="dataResourceId" type="String" mode="OUT" optional="true"/>
    </service>
    
    <service name="otsShowCmsPage" engine="simple" 
        location="org/ofbiz/opentravelsystem/GeneralServices.xml" invoke="showCmsPage" auth="false">
        <description>Show a html page from the content management system and if not exist create with default info</description>
        <attribute name="contentId" type="String" mode="INOUT" optional="false"/>
        <attribute name="dataResourceId" type="String" mode="OUT" optional="true"/>
    </service>
    
    <!-- UserLogin to SecurityGroup services -->
    <service name="otsAddUserLoginToSecurityGroup" engine="simple" location="org/ofbiz/opentravelsystem/GeneralServices.xml" invoke="addUserLoginToSecurityGroup" auth="true">
        <description>Add a UserLogin to a SecurityGroup</description>
        <attribute name="userLoginId" type="String" mode="IN" optional="false"/>
        <attribute name="groupId" type="String" mode="IN" optional="false"/>
        <attribute name="fromDate" type="Timestamp" mode="IN" optional="true"/>
        <attribute name="thruDate" type="Timestamp" mode="IN" optional="true"/>
    </service>
    <service name="otsUpdateUserLoginToSecurityGroup" engine="simple" location="org/ofbiz/opentravelsystem/GeneralServices.xml" invoke="updateUserLoginToSecurityGroup" auth="true">
        <description>Update a UserLogin to SecurityGroup Appl</description>
        <attribute name="userLoginId" type="String" mode="IN" optional="false"/>
        <attribute name="groupId" type="String" mode="IN" optional="false"/>
        <attribute name="fromDate" type="Timestamp" mode="IN" optional="false"/>
        <attribute name="thruDate" type="Timestamp" mode="IN" optional="true"/>
    </service>
    <service name="otsRemoveUserLoginFromSecurityGroup" engine="simple" 
        location="org/ofbiz/opentravelsystem/GeneralServices.xml" invoke="removeUserLoginFromSecurityGroup" auth="true">
        <description>Remove a UserLogin from a SecurityGroup</description>
        <attribute name="userLoginId" type="String" mode="IN" optional="false"/>
        <attribute name="groupId" type="String" mode="IN" optional="false"/>
        <attribute name="fromDate" type="Timestamp" mode="IN" optional="false"/>
    </service>

    <!-- add functions to existing services -->
    <!-- add a prefix to the paymentId -->
    <service name="createPayment" engine="simple" default-entity-name="Payment"
        location="org/ofbiz/opentravelsystem/PaymentServices.xml" invoke="createPayment" auth="true">
        <description>Create a Payment</description>
        <auto-attributes include="pk" mode="OUT" optional="false"/>
        <auto-attributes include="nonpk" mode="IN" optional="true"/>
        <override name="paymentTypeId" optional="false"/>
        <override name="paymentMethodTypeId" optional="false"/>
        <override name="partyIdFrom" optional="false"/>
        <override name="partyIdTo" optional="false"/>
        <override name="statusId" optional="false"/>
        <override name="amount" optional="false"/>
    </service>
    <service name="createPaymentOfbiz" engine="simple" default-entity-name="Payment"
        location="org/ofbiz/accounting/payment/PaymentServices.xml" invoke="createPayment" auth="true">
        <description>Create a Payment</description>
        <auto-attributes include="nonpk" mode="IN" optional="true"/>
        <auto-attributes include="pk" mode="INOUT" optional="true"/>
        <override name="paymentTypeId" optional="false"/>
        <override name="paymentMethodTypeId" optional="false"/>
        <override name="partyIdFrom" optional="false"/>
        <override name="partyIdTo" optional="false"/>
        <override name="statusId" optional="false"/>
        <override name="amount" optional="false"/>
    </service>

    <!-- add a prefix to the purchase invoice -->
    <service name="createInvoice" engine="simple" default-entity-name="Invoice"
        location="org/ofbiz/opentravelsystem/InvoiceServices.xml" invoke="createInvoice">
        <description>Create Invoice Record with company prefix</description>
        <auto-attributes mode="OUT" include="pk" optional="false"/>
        <auto-attributes mode="IN" include="nonpk" optional="true"/>
        <override name="invoiceTypeId" mode="IN" optional="false"/>
        <override name="statusId" mode = "IN" optional="false"/>
    </service>
    <service name="createInvoiceOfbiz" engine="simple" default-entity-name="Invoice"
        location="org/ofbiz/accounting/invoice/InvoiceServices.xml" invoke="createInvoice">
        <description>Create Invoice Record</description>
        <auto-attributes mode="INOUT" include="pk" optional="true"/>
        <auto-attributes mode="IN" include="nonpk" optional="true"/>
        <override name="invoiceTypeId" mode="IN" optional="false"/>
        <override name="statusId" mode = "IN" optional="false"/>
    </service>
    <service name="createProductCategory" default-entity-name="ProductCategory" engine="simple"
        location="org/ofbiz/opentravelsystem/CatalogServices.xml" invoke="createProductCategory">
        <description>Create an ProductCategory</description>
        <auto-attributes include="pk" mode="INOUT" optional="true"/>
        <auto-attributes include="nonpk" mode="IN" optional="true"/>
        <override name="productCategoryTypeId" optional="false"/>
    </service>
    <service name="createProductCategoryOfbiz" default-entity-name="ProductCategory" engine="simple"
        location="org/ofbiz/product/category/CategoryServices.xml" invoke="createProductCategory">
        <description>Create an ProductCategory</description>
        <auto-attributes include="pk" mode="INOUT" optional="true"/>
        <auto-attributes include="nonpk" mode="IN" optional="true"/>
        <override name="productCategoryTypeId" optional="false"/>
    </service>
    <service name="createProduct" default-entity-name="Product" engine="simple"
        location="org/ofbiz/opentravelsystem/CatalogServices.xml" invoke="createProduct">
        <description>Create a Product</description>
        <implements service="interfaceProduct"/>
        <auto-attributes include="pk" mode="INOUT" optional="true"/>
        <override name="productTypeId" optional="false"/>
        <override name="internalName" optional="false"/>
    </service>
    <service name="createProductOfbiz" default-entity-name="Product" engine="simple"
        location="org/ofbiz/product/product/ProductServices.xml" invoke="createProduct" auth="true">
        <description>Create a Product</description>
        <implements service="interfaceProduct"/>
        <auto-attributes include="pk" mode="INOUT" optional="true"/>
        <override name="productTypeId" optional="false"/>
        <override name="internalName" optional="false"/>
    </service>
    <service name="createFixedAsset" default-entity-name="FixedAsset" engine="simple"
        location="org/ofbiz/opentravelsystem/CatalogServices.xml" invoke="createFixedAsset" auth="true">
        <description>Create an FixedAsset</description>
        <auto-attributes include="pk" mode="OUT" optional="false"/>
        <auto-attributes include="nonpk" mode="IN" optional="true"/>
        <override name="fixedAssetTypeId" optional="false"/>
    </service>
    <service name="createFixedAssetOfbiz" default-entity-name="FixedAsset" engine="simple"
        location="org/ofbiz/accounting/fixedasset/FixedAssetServices.xml" invoke="createFixedAsset" auth="true">
        <description>Create an FixedAsset</description>
        <auto-attributes include="pk" mode="INOUT" optional="true"/>
        <auto-attributes include="nonpk" mode="IN" optional="true"/>
        <override name="fixedAssetTypeId" optional="false"/>
    </service>
    <service name="createOrderHeader" default-entity-name="OrderHeader" engine="simple"
        location="org/ofbiz/opentravelsystem/OrderServices.xml" invoke="createOrderHeader" auth="true">
        <description>Create OrderHeader</description>
        <auto-attributes include="pk" mode="OUT" optional="false"/>
        <auto-attributes include="nonpk" mode="IN" optional="true"/>
    </service>
    <service name="createOrderHeaderOfbiz" default-entity-name="OrderHeader" engine="simple"
        location="org/ofbiz/order/order/OrderServices.xml" invoke="createOrderHeader" auth="true">
        <description>Create OrderHeader</description>
        <auto-attributes include="pk" mode="INOUT" optional="true"/>
        <auto-attributes include="nonpk" mode="IN" optional="true"/>
    </service>
    <service name="prepareFind" auth="false" engine="java" invoke="prepareFind" location="org.ofbiz.opentravelsystem.FindServices">
        <description>Generic service to return a entity conditions</description>
        <attribute name="entityName" type="String" mode="IN" optional="false"/>
        <attribute name="inputFields" type="java.util.Map" mode="IN" optional="false"/>
        <attribute name="orderBy" type="String" mode="IN" optional="true"/>
        <attribute name="noConditionFind" type="String" mode="IN" optional="true"><!-- find with no condition (empty entityConditionList) only done when this is Y --></attribute>
        <attribute name="filterByDate" type="String" mode="IN" optional="true"/>
        <attribute name="queryString" type="String" mode="OUT" optional="true"/>
        <attribute name="queryStringMap" type="java.util.Map" mode="OUT" optional="true"/>
        <attribute name="orderByList" type="java.util.List" mode="OUT" optional="true"/>
        <attribute name="entityConditionList" type="org.ofbiz.entity.condition.EntityConditionList" mode="OUT" optional="true"/>
    </service>
    <!--service name="createPerson" engine="simple" default-entity-name="Person"
        location="org/ofbiz/opentravelsystem/PartyServices.xml" invoke="createPerson" auth="false">
        <description>Create a Person</description>
        <auto-attributes mode="OUT" include="pk" optional="true"/>
        <auto-attributes mode="IN" include="nonpk" optional="true"/>
        <attribute name="productStoreId" type="String" mode="IN" optional="false"/>
        <attribute name="statusId" type="String" mode="IN" optional="true"/>
        <attribute name="preferredCurrencyUomId" type="String" mode="IN" optional="true"/>
        <attribute name="description" type="String" mode="IN" optional="true"/>
        <override name="firstName" optional="false"/>
        <override name="lastName" optional="false"/>
    </service>
    <service name="createPersonOfbiz" engine="java" default-entity-name="Person"
        location="org.ofbiz.party.party.PartyServices" invoke="createPerson" auth="false">
        <description>Create a Person</description>
        <auto-attributes mode="INOUT" include="pk" optional="true"/>
        <auto-attributes mode="IN" include="nonpk" optional="true"/>
        <attribute name="statusId" type="String" mode="IN" optional="true"/>
        <attribute name="preferredCurrencyUomId" type="String" mode="IN" optional="true"/>
        <attribute name="description" type="String" mode="IN" optional="true"/>
        <override name="firstName" optional="false"/>
        <override name="lastName" optional="false"/>
    </service>
    <service name="createPartyGroup" engine="simple" default-entity-name="PartyGroup"
        location="org/ofbiz/opentravelsystem/PartyServices.xml" invoke="createPartyGroup" auth="false">
        <description>Create a PartyGroup</description>
        <auto-attributes mode="OUT" include="pk" optional="true"/>
        <auto-attributes mode="IN" include="nonpk" optional="true"/>
        <attribute name="emailproductStoreId" type="String" mode="IN" optional="false"/>
        <attribute name="partyTypeId" type="String" mode="IN" optional="true"/>
        <attribute name="description" type="String" mode="IN" optional="true"/>
        <override name="groupName" optional="false"/>
    </service>
    <service name="createPartyGroupOfbiz" engine="java" default-entity-name="PartyGroup"
        location="org.ofbiz.party.party.PartyServices" invoke="createPartyGroup" auth="false">
        <description>Create a PartyGroup</description>
        <auto-attributes mode="INOUT" include="pk" optional="true"/>
        <auto-attributes mode="IN" include="nonpk" optional="true"/>
        <attribute name="partyTypeId" type="String" mode="IN" optional="true"/>
        <attribute name="description" type="String" mode="IN" optional="true"/>
        <override name="groupName" optional="false"/>
    </service-->
    
    <!-- ContactList Services -->
    <service name="createContactList" default-entity-name="ContactList" engine="simple"
        location="org/ofbiz/opentravelsystem/PartyServices.xml" invoke="createContactList" auth="true">
        <description>Create a ContactList record</description>
        <auto-attributes include="pk" mode="OUT" optional="false"/>
        <auto-attributes include="nonpk" mode="IN" optional="true"/>
        <override name="contactListTypeId" optional="false"/>
        <override name="contactListName" optional="false"/>
    </service>
    <!-- ContactList Services -->
    <service name="createContactListOfbiz" default-entity-name="ContactList" engine="simple"
        location="org/ofbiz/marketing/contact/ContactListServices.xml" invoke="createContactList" auth="true">
        <description>Create a ContactList record</description>
        <auto-attributes include="pk" mode="INOUT" optional="false"/>
        <auto-attributes include="nonpk" mode="IN" optional="true"/>
        <override name="contactListTypeId" optional="false"/>
        <override name="contactListName" optional="false"/>
    </service>
    <!--service name="updatePaymentApplication" default-entity-name="PaymentApplication" engine="simple"
        location="org/ofbiz/opentravelsystem/InvoiceServices.xml" invoke="updatePaymentApplication">
        <description>
            Apply a payment to a Invoice, create/update paymentApplication records, modified version, will apply
            the maximum amount when no amount is supplied.
        </description>
        <auto-attributes mode="IN" include="pk" optional="true"/>
        <auto-attributes mode="IN" include="nonpk" optional="true"/>
        <attribute name="invoiceProcessing" type="String" mode="IN" optional="true"/>
        <override name="paymentId" optional="false"/>        
    </service>
    <service name="updatePaymentApplicationOfbiz" default-entity-name="PaymentApplication" engine="java"
        location="org.ofbiz.accounting.invoice.InvoiceServices" invoke="updatePaymentApplication">
        <description>
            Apply a payment to a Invoice, create/update paymentApplication records
        </description>
        <auto-attributes mode="IN" include="pk" optional="true"/>
        <auto-attributes mode="IN" include="nonpk" optional="true"/>
        <attribute name="invoiceProcessing" type="String" mode="IN" optional="true"/>
        <override name="paymentId" optional="false"/>        
    </service-->
    
</services>
